Workbook
Name ExternalData_1: 'CLEAN DATA'!$A$1:$N$3920

Sheet CLEAN DATA
A1: director_name | B1: num_critic_for_reviews | C1: duration | D1: gross | E1: genres | F1: actor_1_name | G1: movie_title | H1: num_voted_users | I1: num_user_for_reviews | J1: language | K1: country | L1: budget | M1: title_year | N1: imdb_score | O1: Profit
A2: Frank Darabont | B2: 199 | C2: 142 | D2: 28341469 | E2: Crime|Drama | F2: Morgan Freeman | G2: The Shawshank Redemption | H2: 1689764 | I2: 4144 | J2: English | K2: USA | L2: 25000000 | M2: 1994 | N2: 9.3 | O2: ='CLEAN DATA'!$D2-'CLEAN DATA'!$L2 -> 3341469
A3: Francis Ford Coppola | B3: 208 | C3: 175 | D3: 134821952 | E3: Crime|Drama | F3: Al Pacino | G3: The Godfather | H3: 1155770 | I3: 2238 | J3: English | K3: USA | L3: 6000000 | M3: 1972 | N3: 9.2 | O3: ='CLEAN DATA'!$D3-'CLEAN DATA'!$L3 -> 128821952
A4: Christopher Nolan | B4: 645 | C4: 152 | D4: 533316061 | E4: Action|Crime|Drama|Thriller | F4: Christian Bale | G4: The Dark Knight | H4: 1676169 | I4: 4667 | J4: English | K4: USA | L4: 185000000 | M4: 2008 | N4: 9 | O4: ='CLEAN DATA'!$D4-'CLEAN DATA'!$L4 -> 348316061
A5: Francis Ford Coppola | B5: 149 | C5: 220 | D5: 57300000 | E5: Crime|Drama | F5: Robert De Niro | G5: The Godfather: Part II | H5: 790926 | I5: 650 | J5: English | K5: USA | L5: 13000000 | M5: 1974 | N5: 9 | O5: ='CLEAN DATA'!$D5-'CLEAN DATA'!$L5 -> 44300000
A6: Peter Jackson | B6: 328 | C6: 192 | D6: 377019252 | E6: Action|Adventure|Drama|Fantasy | F6: Orlando Bloom | G6: The Lord of the Rings: The Return of the King | H6: 1215718 | I6: 3189 | J6: English | K6: USA | L6: 94000000 | M6: 2003 | N6: 8.9 | O6: ='CLEAN DATA'!$D6-'CLEAN DATA'!$L6 -> 283019252
A7: Steven Spielberg | B7: 174 | C7: 185 | D7: 96067179 | E7: Biography|Drama|History | F7: Liam Neeson | G7: Schindler's List | H7: 865020 | I7: 1273 | J7: English | K7: USA | L7: 22000000 | M7: 1993 | N7: 8.9 | O7: ='CLEAN DATA'!$D7-'CLEAN DATA'!$L7 -> 74067179
A8: Quentin Tarantino | B8: 215 | C8: 178 | D8: 107930000 | E8: Crime|Drama | F8: Bruce Willis | G8: Pulp Fiction | H8: 1324680 | I8: 2195 | J8: English | K8: USA | L8: 8000000 | M8: 1994 | N8: 8.9 | O8: ='CLEAN DATA'!$D8-'CLEAN DATA'!$L8 -> 99930000
A9: Sergio Leone | B9: 181 | C9: 142 | D9: 6100000 | E9: Western | F9: Clint Eastwood | G9: The Good, the Bad and the Ugly | H9: 503509 | I9: 780 | J9: Italian | K9: Italy | L9: 1200000 | M9: 1966 | N9: 8.9 | O9: ='CLEAN DATA'!$D9-'CLEAN DATA'!$L9 -> 4900000
A10: Christopher Nolan | B10: 642 | C10: 148 | D10: 292568851 | E10: Action|Adventure|Sci-Fi|Thriller | F10: Leonardo DiCaprio | G10: Inception | H10: 1468200 | I10: 2803 | J10: English | K10: USA | L10: 160000000 | M10: 2010 | N10: 8.8 | O10: ='CLEAN DATA'!$D10-'CLEAN DATA'!$L10 -> 132568851
A11: Peter Jackson | B11: 297 | C11: 171 | D11: 313837577 | E11: Action|Adventure|Drama|Fantasy | F11: Christopher Lee | G11: The Lord of the Rings: The Fellowship of the Ring | H11: 1238746 | I11: 5060 | J11: English | K11: New Zealand | L11: 93000000 | M11: 2001 | N11: 8.8 | O11: ='CLEAN DATA'!$D11-'CLEAN DATA'!$L11 -> 220837577
A12: David Fincher | B12: 315 | C12: 151 | D12: 37023395 | E12: Drama | F12: Brad Pitt | G12: Fight Club | H12: 1347461 | I12: 2968 | J12: English | K12: USA | L12: 63000000 | M12: 1999 | N12: 8.8 | O12: ='CLEAN DATA'!$D12-'CLEAN DATA'!$L12 -> -25976605
A13: Robert Zemeckis | B13: 149 | C13: 142 | D13: 329691196 | E13: Comedy|Drama | F13: Tom Hanks | G13: Forrest Gump | H13: 1251222 | I13: 1398 | J13: English | K13: USA | L13: 55000000 | M13: 1994 | N13: 8.8 | O13: ='CLEAN DATA'!$D13-'CLEAN DATA'!$L13 -> 274691196
... A552: Kay Pollak | B552: 34 | C552: 133 | D552: 9910 | E552: Comedy|Drama|Music|Romance | F552: Michael Nyqvist | G552: As It Is in Heaven | H552: 13543 | I552: 94 | J552: Swedish | K552: Sweden | L552: 25000000 | M552: 2004 | N552: 7.6 | O552: ='CLEAN DATA'!$D552-'CLEAN DATA'!$L552 -> -24990090
A553: Pan Nalin | B553: 15 | C553: 102 | D553: 16892 | E553: Documentary | G553: Ayurveda: Art of Being | H553: 341 | I553: 12 | J553: English | K553: India | L553: 300000 | M553: 2001 | N553: 7.6 | O553: ='CLEAN DATA'!$D553-'CLEAN DATA'!$L553 -> -283108
A554: Kevin Jordan | B554: 21 | C554: 90 | D554: 277233 | E554: Comedy|Romance | F554: Derick Martini | G554: Smiling Fish & Goat on Fire | H554: 2631 | I554: 26 | J554: English | K554: USA | L554: 40000 | M554: 1999 | N554: 7.6 | O554: ='CLEAN DATA'!$D554-'CLEAN DATA'!$L554 -> 237233
A555: Joss Whedon | B555: 635 | C555: 141 | D555: 458991599 | E555: Action|Adventure|Sci-Fi | F555: Chris Hemsworth | G555: Avengers: Age of Ultron | H555: 462669 | I555: 1117 | J555: English | K555: USA | L555: 250000000 | M555: 2015 | N555: 7.5 | O555: ='CLEAN DATA'!$D555-'CLEAN DATA'!$L555 -> 208991599
A556: David Yates | B556: 375 | C556: 153 | D556: 301956980 | E556: Adventure|Family|Fantasy|Mystery | F556: Alan Rickman | G556: Harry Potter and the Half-Blood Prince | H556: 321795 | I556: 973 | J556: English | K556: UK | L556: 250000000 | M556: 2009 | N556: 7.5 | O556: ='CLEAN DATA'!$D556-'CLEAN DATA'!$L556 -> 51956980
A557: Peter Jackson | B557: 422 | C557: 164 | D557: 255108370 | E557: Adventure|Fantasy | F557: Aidan Turner | G557: The Hobbit: The Battle of the Five Armies | H557: 354228 | I557: 802 | J557: English | K557: New Zealand | L557: 250000000 | M557: 2014 | N557: 7.5 | O557: ='CLEAN DATA'!$D557-'CLEAN DATA'!$L557 -> 5108370
A558: Justin Lin | B558: 322 | C558: 122 | D558: 130468626 | E558: Action|Adventure|Sci-Fi|Thriller | F558: Sofia Boutella | G558: Star Trek Beyond | H558: 53607 | I558: 432 | J558: English | K558: USA | L558: 185000000 | M558: 2016 | N558: 7.5 | O558: ='CLEAN DATA'!$D558-'CLEAN DATA'!$L558 -> -54531374
A559: Martin Scorsese | B559: 682 | C559: 126 | D559: 73820094 | E559: Adventure|Drama|Family|Mystery | F559: Chloë Grace Moretz | G559: Hugo | H559: 245333 | I559: 678 | J559: English | K559: USA | L559: 170000000 | M559: 2011 | N559: 7.5 | O559: ='CLEAN DATA'!$D559-'CLEAN DATA'!$L559 -> -96179906
A560: David Yates | B560: 329 | C560: 138 | D560: 292000866 | E560: Adventure|Family|Fantasy|Mystery | F560: Robert Pattinson | G560: Harry Potter and the Order of the Phoenix | H560: 355137 | I560: 1108 | J560: English | K560: UK | L560: 150000000 | M560: 2007 | N560: 7.5 | O560: ='CLEAN DATA'!$D560-'CLEAN DATA'!$L560 -> 142000866
A561: Chris Columbus | B561: 258 | C561: 159 | D561: 317557891 | E561: Adventure|Family|Fantasy | F561: Daniel Radcliffe | G561: Harry Potter and the Sorcerer's Stone | H561: 444683 | I561: 1571 | J561: English | K561: UK | L561: 125000000 | M561: 2001 | N561: 7.5 | O561: ='CLEAN DATA'!$D561-'CLEAN DATA'!$L561 -> 192557891
A562: Bryan Singer | B562: 289 | C562: 134 | D562: 214948780 | E562: Action|Adventure|Fantasy|Sci-Fi|Thriller | F562: Hugh Jackman | G562: X-Men 2 | H562: 405973 | I562: 1055 | J562: English | K562: Canada | L562: 110000000 | M562: 2003 | N562: 7.5 | O562: ='CLEAN DATA'!$D562-'CLEAN DATA'!$L562 -> 104948780
A563: Guy Ritchie | B563: 382 | C563: 129 | D563: 186830669 | E563: Action|Adventure|Crime|Mystery|Thriller | F563: Robert Downey Jr. | G563: Sherlock Holmes: A Game of Shadows | H563: 338635 | I563: 412 | J563: English | K563: USA | L563: 125000000 | M563: 2011 | N563: 7.5 | O563: ='CLEAN DATA'!$D563-'CLEAN DATA'!$L563 -> 61830669
A564: Paul Verhoeven | B564: 196 | C564: 113 | D564: 119412921 | E564: Action|Sci-Fi | F564: Ronny Cox | G564: Total Recall | H564: 240241 | I564: 391 | J564: English | K564: USA | L564: 65000000 | M564: 1990 | N564: 7.5 | O564: ='CLEAN DATA'!$D564-'CLEAN DATA'!$L564 -> 54412921
A565: Martin Scorsese | B565: 267 | C565: 170 | D565: 102608827 | E565: Biography|Drama | F565: Leonardo DiCaprio | G565: The Aviator | H565: 264318 | I565: 799 | J565: English | K565: USA | L565: 110000000 | M565: 2004 | N565: 7.5 | O565: ='CLEAN DATA'!$D565-'CLEAN DATA'!$L565 -> -7391173
... A744: Mira Nair | B744: 137 | C744: 114 | D744: 13876974 | E744: Comedy|Drama|Romance | F744: Naseeruddin Shah | G744: Monsoon Wedding | H744: 19397 | I744: 214 | J744: Hindi | K744: India | L744: 7000000 | M744: 2001 | N744: 7.4 | O744: ='CLEAN DATA'!$D744-'CLEAN DATA'!$L744 -> 6876974
A745: Léa Pool | B745: 23 | C745: 97 | D745: 24784 | E745: Documentary | G745: Pink Ribbons, Inc. | H745: 591 | I745: 10 | J745: English | K745: Canada | L745: 1200000 | M745: 2011 | N745: 7.4 | O745: ='CLEAN DATA'!$D745-'CLEAN DATA'!$L745 -> -1175216
A746: Derek Cianfrance | B746: 377 | C746: 112 | D746: 9701559 | E746: Drama|Romance | F746: Ryan Gosling | G746: Blue Valentine | H746: 141425 | I746: 283 | J746: English | K746: USA | L746: 3500000 | M746: 2010 | N746: 7.4 | O746: ='CLEAN DATA'!$D746-'CLEAN DATA'!$L746 -> 6201559
A747: Duncan Tucker | B747: 169 | C747: 103 | D747: 9013113 | E747: Adventure|Comedy|Drama | F747: Kevin Zegers | G747: Transamerica | H747: 36321 | I747: 230 | J747: English | K747: USA | L747: 1000000 | M747: 2005 | N747: 7.4 | O747: ='CLEAN DATA'!$D747-'CLEAN DATA'!$L747 -> 8013113
A748: Morgan Neville | B748: 149 | C748: 91 | D748: 4946250 | E748: Documentary|Music | F748: Sheryl Crow | G748: 20 Feet from Stardom | H748: 9540 | I748: 80 | J748: English | K748: USA | L748: 1000000 | M748: 2013 | N748: 7.4 | O748: ='CLEAN DATA'!$D748-'CLEAN DATA'!$L748 -> 3946250
A749: Goran Dukic | B749: 117 | C749: 88 | D749: 104077 | E749: Comedy|Drama|Fantasy|Romance | F749: Leslie Bibb | G749: Wristcutters: A Love Story | H749: 46076 | I749: 88 | J749: English | K749: USA | L749: 1000000 | M749: 2006 | N749: 7.4 | O749: ='CLEAN DATA'!$D749-'CLEAN DATA'!$L749 -> -895923
A750: Siddiq Barmak | B750: 105 | C750: 83 | D750: 1127331 | E750: Drama | F750: Marina Golbahari | G750: Osama | H750: 7559 | I750: 77 | J750: Dari | K750: Afghanistan | L750: 46000 | M750: 2003 | N750: 7.4 | O750: ='CLEAN DATA'!$D750-'CLEAN DATA'!$L750 -> 1081331
A751: Julie Taymor | B751: 156 | C751: 133 | D751: 24343673 | E751: Drama|Fantasy|Musical|Romance | F751: Jim Sturgess | G751: Across the Universe | H751: 91863 | I751: 524 | J751: English | K751: USA | L751: 45000000 | M751: 2007 | N751: 7.4 | O751: ='CLEAN DATA'!$D751-'CLEAN DATA'!$L751 -> -20656327
A752: Doug Liman | B752: 77 | C752: 96 | D752: 4505922 | E752: Comedy|Drama | F752: Jon Favreau | G752: Swingers | H752: 63951 | I752: 252 | J752: English | K752: USA | L752: 200000 | M752: 1996 | N752: 7.4 | O752: ='CLEAN DATA'!$D752-'CLEAN DATA'!$L752 -> 4305922
A753: Michel Orion Scott | B753: 29 | C753: 93 | D753: 155984 | E753: Documentary | F753: Temple Grandin | G753: The Horse Boy | H753: 586 | I753: 9 | J753: English | K753: USA | L753: 160000 | M753: 2009 | N753: 7.4 | O753: ='CLEAN DATA'!$D753-'CLEAN DATA'!$L753 -> -4016
A754: Kiyoshi Kurosawa | B754: 78 | C754: 111 | D754: 94596 | E754: Crime|Horror|Mystery|Thriller | F754: Kôji Yakusho | G754: The Cure | H754: 6318 | I754: 50 | J754: Japanese | K754: Japan | L754: 1000000 | M754: 1997 | N754: 7.4 | O754: ='CLEAN DATA'!$D754-'CLEAN DATA'!$L754 -> -905404
A755: Gore Verbinski | B755: 313 | C755: 151 | D755: 423032628 | E755: Action|Adventure|Fantasy | F755: Johnny Depp | G755: Pirates of the Caribbean: Dead Man's Chest | H755: 522040 | I755: 1832 | J755: English | K755: USA | L755: 225000000 | M755: 2006 | N755: 7.3 | O755: ='CLEAN DATA'!$D755-'CLEAN DATA'!$L755 -> 198032628
A756: Sam Raimi | B756: 300 | C756: 135 | D756: 373377893 | E756: Action|Adventure|Fantasy|Romance | F756: J.K. Simmons | G756: Spider-Man 2 | H756: 411164 | I756: 1303 | J756: English | K756: USA | L756: 200000000 | M756: 2004 | N756: 7.3 | O756: ='CLEAN DATA'!$D756-'CLEAN DATA'!$L756 -> 173377893
A757: Dan Scanlon | B757: 376 | C757: 104 | D757: 268488329 | E757: Adventure|Animation|Comedy|Family|Fantasy | F757: Steve Buscemi | G757: Monsters University | H757: 235025 | I757: 265 | J757: English | K757: USA | L757: 200000000 | M757: 2013 | N757: 7.3 | O757: ='CLEAN DATA'!$D757-'CLEAN DATA'!$L757 -> 68488329
... A1013: Michel Gondry | B1013: 114 | C1013: 100 | D1013: 11694528 | E1013: Comedy|Documentary|Music | F1013: Common | G1013: Dave Chappelle's Block Party | H1013: 7721 | I1013: 72 | J1013: English | K1013: USA | L1013: 3000000 | M1013: 2005 | N1013: 7.2 | O1013: ='CLEAN DATA'!$D1013-'CLEAN DATA'!$L1013 -> 8694528
A1014: Michael Landon Jr. | B1014: 5 | C1014: 87 | D1014: 252726 | E1014: Drama|Family|Western | F1014: William Morgan Sheppard | G1014: Love's Abiding Joy | H1014: 1289 | I1014: 18 | K1014: USA | L1014: 3000000 | M1014: 2006 | N1014: 7.2 | O1014: ='CLEAN DATA'!$D1014-'CLEAN DATA'!$L1014 -> -2747274
A1015: Nacho Vigalondo | B1015: 173 | C1015: 66 | D1015: 38108 | E1015: Horror|Mystery|Sci-Fi|Thriller | F1015: Karra Elejalde | G1015: Timecrimes | H1015: 40878 | I1015: 124 | J1015: Spanish | K1015: Spain | L1015: 2600000 | M1015: 2007 | N1015: 7.2 | O1015: ='CLEAN DATA'!$D1015-'CLEAN DATA'!$L1015 -> -2561892
A1016: Robert Fontaine | B1016: 4 | C1016: 125 | D1016: 3330 | E1016: Crime|Drama | F1016: Michael Derek | G1016: Mi America | H1016: 22 | I1016: 1 | J1016: English | K1016: USA | L1016: 2100000 | M1016: 2015 | N1016: 7.2 | O1016: ='CLEAN DATA'!$D1016-'CLEAN DATA'!$L1016 -> -2096670
A1017: Chris Eyre | B1017: 56 | C1017: 89 | D1017: 6719300 | E1017: Comedy|Drama | F1017: Michael Greyeyes | G1017: Smoke Signals | H1017: 8224 | I1017: 132 | J1017: English | K1017: Canada | L1017: 2000000 | M1017: 1998 | N1017: 7.2 | O1017: ='CLEAN DATA'!$D1017-'CLEAN DATA'!$L1017 -> 4719300
A1018: Debra Granik | B1018: 365 | C1018: 100 | D1018: 6531491 | E1018: Drama | F1018: Jennifer Lawrence | G1018: Winter's Bone | H1018: 111658 | I1018: 297 | J1018: English | K1018: USA | L1018: 2000000 | M1018: 2010 | N1018: 7.2 | O1018: ='CLEAN DATA'!$D1018-'CLEAN DATA'!$L1018 -> 4531491
A1019: Jamal Hill | B1019: 10 | C1019: 89 | D1019: 444044 | E1019: Drama | F1019: Logan Browning | G1019: Brotherly Love | H1019: 744 | I1019: 19 | J1019: English | K1019: USA | L1019: 1900000 | M1019: 2015 | N1019: 7.2 | O1019: ='CLEAN DATA'!$D1019-'CLEAN DATA'!$L1019 -> -1455956
A1020: Nadine Labaki | B1020: 109 | C1020: 95 | D1020: 1060591 | E1020: Comedy|Drama|Romance | F1020: Yasmine Al Massri | G1020: Caramel | H1020: 9750 | I1020: 66 | J1020: Arabic | K1020: France | L1020: 1300000 | M1020: 2007 | N1020: 7.2 | O1020: ='CLEAN DATA'!$D1020-'CLEAN DATA'!$L1020 -> -239409
A1021: François Truffaut | B1021: 35 | C1021: 123 | D1021: 26893 | E1021: Crime|Drama|Romance | F1021: Catherine Deneuve | G1021: Mississippi Mermaid | H1021: 4391 | I1021: 26 | J1021: French | K1021: France | L1021: 1600000 | M1021: 1969 | N1021: 7.2 | O1021: ='CLEAN DATA'!$D1021-'CLEAN DATA'!$L1021 -> -1573107
A1022: Atom Egoyan | B1022: 53 | C1022: 103 | D1022: 5132222 | E1022: Drama|Mystery|Romance | F1022: Bruce Greenwood | G1022: Exotica | H1022: 14112 | I1022: 83 | J1022: English | K1022: Canada | L1022: 2000000 | M1022: 1994 | N1022: 7.2 | O1022: ='CLEAN DATA'!$D1022-'CLEAN DATA'!$L1022 -> 3132222
A1023: Henry Bean | B1023: 84 | C1023: 98 | D1023: 406035 | E1023: Drama | F1023: Ryan Gosling | G1023: The Believer | H1023: 30314 | I1023: 159 | J1023: English | K1023: USA | L1023: 1500000 | M1023: 2001 | N1023: 7.2 | O1023: ='CLEAN DATA'!$D1023-'CLEAN DATA'!$L1023 -> -1093965
A1024: Steve Buscemi | B1024: 43 | C1024: 95 | D1024: 695229 | E1024: Comedy|Drama | F1024: Steve Buscemi | G1024: Trees Lounge | H1024: 11369 | I1024: 65 | J1024: English | K1024: USA | L1024: 1300000 | M1024: 1996 | N1024: 7.2 | O1024: ='CLEAN DATA'!$D1024-'CLEAN DATA'!$L1024 -> -604771
A1025: Steven Soderbergh | B1025: 58 | C1025: 100 | D1025: 24741700 | E1025: Drama | F1025: Peter Gallagher | G1025: Sex, Lies, and Videotape | H1025: 37785 | I1025: 95 | J1025: English | K1025: USA | L1025: 1200000 | M1025: 1989 | N1025: 7.2 | O1025: ='CLEAN DATA'!$D1025-'CLEAN DATA'!$L1025 -> 23541700
A1026: Tom Sanchez | B1026: 1 | C1026: 110 | D1026: 3830 | E1026: Comedy|Drama | F1026: Nataniel Sánchez | G1026: The Knife of Don Juan | H1026: 27 | I1026: 1 | J1026: Spanish | K1026: USA | L1026: 1200000 | M1026: 2013 | N1026: 7.2 | O1026: ='CLEAN DATA'!$D1026-'CLEAN DATA'!$L1026 -> -1196170
... A1037: Ryan Fleck | B1037: 208 | C1037: 106 | D1037: 2694973 | E1037: Drama | F1037: Ryan Gosling | G1037: Half Nelson | H1037: 70885 | I1037: 189 | J1037: English | K1037: USA | L1037: 700000 | M1037: 2006 | N1037: 7.2 | O1037: ='CLEAN DATA'!$D1037-'CLEAN DATA'!$L1037 -> 1994973
A1038: U. Roberto Romano | B1038: 3 | C1038: 80 | D1038: 2245 | E1038: Documentary | G1038: The Harvest/La Cosecha | H1038: 57 | I1038: 2 | J1038: English | K1038: USA | L1038: 560000 | M1038: 2011 | N1038: 7.2 | O1038: ='CLEAN DATA'!$D1038-'CLEAN DATA'!$L1038 -> -557755
A1039: Jonathan Caouette | B1039: 72 | C1039: 88 | D1039: 592014 | E1039: Biography|Documentary | F1039: Greg Ayres | G1039: Tarnation | H1039: 5709 | I1039: 114 | J1039: English | K1039: USA | L1039: 218 | M1039: 2003 | N1039: 7.2 | O1039: ='CLEAN DATA'!$D1039-'CLEAN DATA'!$L1039 -> 591796
A1040: Mor Loushy | B1040: 23 | C1040: 84 | D1040: 34151 | E1040: Documentary|History | F1040: Amos Oz | G1040: Censored Voices | H1040: 186 | I1040: 3 | J1040: Hebrew | K1040: Israel | L1040: 450000 | M1040: 2015 | N1040: 7.2 | O1040: ='CLEAN DATA'!$D1040-'CLEAN DATA'!$L1040 -> -415849
A1041: Justin Lin | B1041: 51 | C1041: 98 | D1041: 3799339 | E1041: Crime|Drama|Romance | F1041: Parry Shen | G1041: Better Luck Tomorrow | H1041: 8000 | I1041: 138 | J1041: English | K1041: USA | L1041: 250000 | M1041: 2002 | N1041: 7.2 | O1041: ='CLEAN DATA'!$D1041-'CLEAN DATA'!$L1041 -> 3549339
A1042: Maurizio Benazzo | B1042: 15 | C1042: 85 | D1042: 381225 | E1042: Documentary | F1042: The Dalai Lama | G1042: Short Cut to Nirvana: Kumbh Mela | H1042: 131 | I1042: 13 | J1042: English | K1042: USA | L1042: 200000 | M1042: 2004 | N1042: 7.2 | O1042: ='CLEAN DATA'!$D1042-'CLEAN DATA'!$L1042 -> 181225
A1043: Gore Verbinski | B1043: 302 | C1043: 169 | D1043: 309404152 | E1043: Action|Adventure|Fantasy | F1043: Johnny Depp | G1043: Pirates of the Caribbean: At World's End | H1043: 471220 | I1043: 1238 | J1043: English | K1043: USA | L1043: 300000000 | M1043: 2007 | N1043: 7.1 | O1043: ='CLEAN DATA'!$D1043-'CLEAN DATA'!$L1043 -> 9404152
A1044: Michael Bay | B1044: 396 | C1044: 144 | D1044: 318759914 | E1044: Action|Adventure|Sci-Fi | F1044: Zack Ward | G1044: Transformers | H1044: 513158 | I1044: 1782 | J1044: English | K1044: USA | L1044: 150000000 | M1044: 2007 | N1044: 7.1 | O1044: ='CLEAN DATA'!$D1044-'CLEAN DATA'!$L1044 -> 168759914
A1045: Alan Taylor | B1045: 486 | C1045: 112 | D1045: 206360018 | E1045: Action|Adventure|Fantasy | F1045: Chris Hemsworth | G1045: Thor: The Dark World | H1045: 414070 | I1045: 532 | J1045: English | K1045: USA | L1045: 170000000 | M1045: 2013 | N1045: 7.1 | O1045: ='CLEAN DATA'!$D1045-'CLEAN DATA'!$L1045 -> 36360018
A1046: Paul Greengrass | B1046: 267 | C1046: 123 | D1046: 108521835 | E1046: Action|Thriller | F1046: Matt Damon | G1046: Jason Bourne | H1046: 40123 | I1046: 297 | J1046: English | K1046: UK | L1046: 120000000 | M1046: 2016 | N1046: 7.1 | O1046: ='CLEAN DATA'!$D1046-'CLEAN DATA'!$L1046 -> -11478165
A1047: Roland Emmerich | B1047: 192 | C1047: 142 | D1047: 113330342 | E1047: Action|Drama|History|War | F1047: Heath Ledger | G1047: The Patriot | H1047: 207613 | I1047: 1144 | J1047: English | K1047: USA | L1047: 110000000 | M1047: 2000 | N1047: 7.1 | O1047: ='CLEAN DATA'!$D1047-'CLEAN DATA'!$L1047 -> 3330342
A1048: Shawn Levy | B1048: 327 | C1048: 127 | D1048: 85463309 | E1048: Action|Drama|Sci-Fi|Sport | F1048: Hugh Jackman | G1048: Real Steel | H1048: 254841 | I1048: 426 | J1048: English | K1048: USA | L1048: 110000000 | M1048: 2011 | N1048: 7.1 | O1048: ='CLEAN DATA'!$D1048-'CLEAN DATA'!$L1048 -> -24536691
A1049: Alex Proyas | B1049: 225 | C1049: 115 | D1049: 144795350 | E1049: Action|Mystery|Sci-Fi|Thriller | F1049: Will Smith | G1049: I, Robot | H1049: 387632 | I1049: 789 | J1049: English | K1049: USA | L1049: 120000000 | M1049: 2004 | N1049: 7.1 | O1049: ='CLEAN DATA'!$D1049-'CLEAN DATA'!$L1049 -> 24795350
A1050: Ron Clements | B1050: 228 | C1050: 97 | D1050: 104374107 | E1050: Animation|Family|Fantasy|Musical|Romance | F1050: Oprah Winfrey | G1050: The Princess and the Frog | H1050: 89351 | I1050: 214 | J1050: English | K1050: USA | L1050: 105000000 | M1050: 2009 | N1050: 7.1 | O1050: ='CLEAN DATA'!$D1050-'CLEAN DATA'!$L1050 -> -625893
... A3020: David Hackl | B3020: 160 | C3020: 95 | D3020: 56729973 | E3020: Horror|Mystery | F3020: Julie Benz | G3020: Saw V | H3020: 88529 | I3020: 262 | J3020: English | K3020: USA | L3020: 10800000 | M3020: 2008 | N3020: 5.8 | O3020: ='CLEAN DATA'!$D3020-'CLEAN DATA'!$L3020 -> 45929973
A3021: Christopher Cain | B3021: 43 | C3021: 111 | D3021: 1066555 | E3021: Drama|History|Romance|Western | F3021: Jon Gries | G3021: September Dawn | H3021: 2618 | I3021: 111 | K3021: USA | L3021: 11000000 | M3021: 2007 | N3021: 5.8 | O3021: ='CLEAN DATA'!$D3021-'CLEAN DATA'!$L3021 -> -9933445
A3022: Robert Iscove | B3022: 96 | C3022: 95 | D3022: 63319509 | E3022: Comedy|Romance | F3022: Paul Walker | G3022: She's All That | H3022: 67115 | I3022: 389 | J3022: English | K3022: USA | L3022: 10000000 | M3022: 1999 | N3022: 5.8 | O3022: ='CLEAN DATA'!$D3022-'CLEAN DATA'!$L3022 -> 53319509
A3023: Marcus Raboy | B3023: 26 | C3023: 85 | D3023: 32983713 | E3023: Comedy|Drama | F3023: John Witherspoon | G3023: Friday After Next | H3023: 19284 | I3023: 66 | J3023: English | K3023: USA | L3023: 20000000 | M3023: 2002 | N3023: 5.8 | O3023: ='CLEAN DATA'!$D3023-'CLEAN DATA'!$L3023 -> 12983713
A3024: Keenen Ivory Wayans | B3024: 8 | C3024: 100 | D3024: 29392418 | E3024: Action|Comedy|Crime | F3024: Jada Pinkett Smith | G3024: A Low Down Dirty Shame | H3024: 3924 | I3024: 26 | J3024: English | K3024: USA | L3024: 10000000 | M3024: 1994 | N3024: 5.8 | O3024: ='CLEAN DATA'!$D3024-'CLEAN DATA'!$L3024 -> 19392418
A3025: Tommy O'Haver | B3025: 63 | C3025: 87 | D3025: 11560259 | E3025: Comedy|Romance | F3025: Mila Kunis | G3025: Get Over It | H3025: 15617 | I3025: 180 | J3025: English | K3025: USA | L3025: 22000000 | M3025: 2001 | N3025: 5.8 | O3025: ='CLEAN DATA'!$D3025-'CLEAN DATA'!$L3025 -> -10439741
A3026: Timothy Björklund | B3026: 33 | C3026: 74 | D3026: 6491350 | E3026: Animation|Comedy|Family|Fantasy|Musical | F3026: Nathan Lane | G3026: Teacher's Pet | H3026: 1231 | I3026: 26 | J3026: English | K3026: USA | L3026: 10000000 | M3026: 2004 | N3026: 5.8 | O3026: ='CLEAN DATA'!$D3026-'CLEAN DATA'!$L3026 -> -3508650
A3027: Frank Coraci | B3027: 188 | C3027: 120 | D3027: 24004159 | E3027: Action|Adventure|Comedy | F3027: Jim Broadbent | G3027: Around the World in 80 Days | H3027: 68722 | I3027: 191 | J3027: English | K3027: USA | L3027: 110000000 | M3027: 2004 | N3027: 5.8 | O3027: ='CLEAN DATA'!$D3027-'CLEAN DATA'!$L3027 -> -85995841
A3028: Spike Lee | B3028: 22 | C3028: 121 | D3028: 14545844 | E3028: Comedy|Drama|Musical | F3028: Tisha Campbell-Martin | G3028: School Daze | H3028: 4756 | I3028: 38 | J3028: English | K3028: USA | L3028: 6500000 | M3028: 1988 | N3028: 5.8 | O3028: ='CLEAN DATA'!$D3028-'CLEAN DATA'!$L3028 -> 8045844
A3029: David Atkins | B3029: 84 | C3029: 95 | D3029: 2025238 | E3029: Comedy|Crime|Drama|Thriller | F3029: Chelcie Ross | G3029: Novocaine | H3029: 9589 | I3029: 105 | J3029: English | K3029: USA | L3029: 6000000 | M3029: 2001 | N3029: 5.8 | O3029: ='CLEAN DATA'!$D3029-'CLEAN DATA'!$L3029 -> -3974762
A3030: Kate Barker-Froyland | B3030: 43 | C3030: 86 | D3030: 20200 | E3030: Drama|Music | F3030: Anne Hathaway | G3030: Song One | H3030: 6797 | I3030: 21 | J3030: English | K3030: USA | L3030: 6000000 | M3030: 2014 | N3030: 5.8 | O3030: ='CLEAN DATA'!$D3030-'CLEAN DATA'!$L3030 -> -5979800
A3031: Henry Joost | B3031: 251 | C3031: 94 | D3031: 104007828 | E3031: Horror | F3031: Johanna Braddy | G3031: Paranormal Activity 3 | H3031: 76828 | I3031: 314 | J3031: English | K3031: USA | L3031: 5000000 | M3031: 2011 | N3031: 5.8 | O3031: ='CLEAN DATA'!$D3031-'CLEAN DATA'!$L3031 -> 99007828
A3032: Ernie Barbarash | B3032: 29 | C3032: 103 | D3032: 8691 | E3032: Action|Adventure | F3032: Michael Jai White | G3032: Falcon Rising | H3032: 4952 | I3032: 32 | J3032: English | K3032: USA | L3032: 4500000 | M3032: 2014 | N3032: 5.8 | O3032: ='CLEAN DATA'!$D3032-'CLEAN DATA'!$L3032 -> -4491309
A3033: Joe Wright | B3033: 256 | C3033: 111 | D3033: 34964818 | E3033: Adventure|Family|Fantasy | F3033: Hugh Jackman | G3033: Pan | H3033: 39975 | I3033: 186 | J3033: English | K3033: USA | L3033: 150000000 | M3033: 2015 | N3033: 5.8 | O3033: ='CLEAN DATA'!$D3033-'CLEAN DATA'!$L3033 -> -115035182
... A3293: Tobe Hooper | B3293: 159 | C3293: 101 | D3293: 8025872 | E3293: Comedy|Horror | F3293: Bill Johnson | G3293: The Texas Chainsaw Massacre 2 | H3293: 19234 | I3293: 258 | J3293: English | K3293: USA | L3293: 4700000 | M3293: 1986 | N3293: 5.5 | O3293: ='CLEAN DATA'!$D3293-'CLEAN DATA'!$L3293 -> 3325872
A3294: Anthony O'Brien | B3294: 19 | C3294: 81 | E3294: Adventure|Drama|Western | F3294: James Ransone | G3294: The Timber | H3294: 1274 | I3294: 17 | J3294: English | K3294: USA | L3294: 2100000 | M3294: 2015 | N3294: 5.5 | O3294: ='CLEAN DATA'!$D3294-'CLEAN DATA'!$L3294 -> -2100000
A3295: Chris Shadley | B3295: 25 | C3295: 83 | E3295: Crime|Drama|Horror|Mystery|Thriller | F3295: Daniel Baldwin | G3295: Nine Dead | H3295: 9280 | I3295: 64 | J3295: English | K3295: USA | L3295: 2000000 | M3295: 2010 | N3295: 5.5 | O3295: ='CLEAN DATA'!$D3295-'CLEAN DATA'!$L3295 -> -2000000
A3296: J. Lee Thompson | B3296: 62 | C3296: 96 | E3296: Action|Sci-Fi | F3296: Roddy McDowall | G3296: Battle for the Planet of the Apes | H3296: 22764 | I3296: 91 | J3296: English | K3296: USA | L3296: 1800000 | M3296: 1973 | N3296: 5.5 | O3296: ='CLEAN DATA'!$D3296-'CLEAN DATA'!$L3296 -> -1800000
A3297: Simeon Rice | B3297: 6 | C3297: 93 | E3297: Action|Horror|Thriller | F3297: Ward G. Smith | G3297: Unsullied | H3297: 95 | I3297: 3 | J3297: English | K3297: USA | L3297: 1500000 | M3297: 2014 | N3297: 5.5 | O3297: ='CLEAN DATA'!$D3297-'CLEAN DATA'!$L3297 -> -1500000
A3298: Edward Dmytryk | B3298: 10 | C3298: 113 | E3298: Western | F3298: Brigitte Bardot | G3298: Shalako | H3298: 1978 | I3298: 41 | J3298: English | K3298: UK | L3298: 1455000 | M3298: 1968 | N3298: 5.5 | O3298: ='CLEAN DATA'!$D3298-'CLEAN DATA'!$L3298 -> -1455000
A3299: Jon Knautz | B3299: 63 | C3299: 99 | E3299: Horror|Thriller | F3299: Camren Bicondova | G3299: Girl House | H3299: 4948 | I3299: 33 | J3299: English | K3299: Canada | L3299: 3150000 | M3299: 2014 | N3299: 5.5 | O3299: ='CLEAN DATA'!$D3299-'CLEAN DATA'!$L3299 -> -3150000
A3300: Douglas Cheek | B3300: 77 | C3300: 96 | E3300: Horror|Sci-Fi | F3300: Daniel Stern | G3300: C.H.U.D. | H3300: 7528 | I3300: 88 | J3300: English | K3300: USA | L3300: 1250000 | M3300: 1984 | N3300: 5.5 | O3300: ='CLEAN DATA'!$D3300-'CLEAN DATA'!$L3300 -> -1250000
A3301: Scott Derrickson | B3301: 276 | C3301: 104 | D3301: 79363785 | E3301: Drama|Sci-Fi|Thriller | F3301: Keanu Reeves | G3301: The Day the Earth Stood Still | H3301: 139426 | I3301: 698 | J3301: English | K3301: USA | L3301: 80000000 | M3301: 2008 | N3301: 5.5 | O3301: ='CLEAN DATA'!$D3301-'CLEAN DATA'!$L3301 -> -636215
A3302: Benjamin Dickinson | B3302: 36 | C3302: 97 | D3302: 62480 | E3302: Drama|Sci-Fi | F3302: Nora Zehetner | G3302: Creative Control | H3302: 1048 | I3302: 7 | J3302: English | K3302: USA | L3302: 1000000 | M3302: 2015 | N3302: 5.5 | O3302: ='CLEAN DATA'!$D3302-'CLEAN DATA'!$L3302 -> -937520
A3303: Ti West | B3303: 292 | C3303: 101 | D3303: 77501 | E3303: Horror | F3303: Lena Dunham | G3303: The Innkeepers | H3303: 27260 | I3303: 247 | J3303: English | K3303: USA | L3303: 750000 | M3303: 2011 | N3303: 5.5 | O3303: ='CLEAN DATA'!$D3303-'CLEAN DATA'!$L3303 -> -672499
A3304: Jesse Peretz | B3304: 16 | C3304: 94 | D3304: 40542 | E3304: Drama|Romance | F3304: Robert John Burke | G3304: First Love, Last Rites | H3304: 294 | I3304: 16 | J3304: English | K3304: USA | L3304: 300000 | M3304: 1997 | N3304: 5.5 | O3304: ='CLEAN DATA'!$D3304-'CLEAN DATA'!$L3304 -> -259458
A3305: Greg Harrison | B3305: 43 | C3305: 78 | D3305: 191309 | E3305: Drama|Mystery|Thriller | F3305: Amir Talai | G3305: November | H3305: 2787 | I3305: 64 | J3305: English | K3305: USA | L3305: 150000 | M3305: 2004 | N3305: 5.5 | O3305: ='CLEAN DATA'!$D3305-'CLEAN DATA'!$L3305 -> 41309
A3306: Melvin Van Peebles | B3306: 38 | C3306: 97 | D3306: 15180000 | E3306: Crime|Drama|Thriller | F3306: John Amos | G3306: Sweet Sweetback's Baadasssss Song | H3306: 3340 | I3306: 50 | J3306: English | K3306: USA | L3306: 500000 | M3306: 1971 | N3306: 5.5 | O3306: ='CLEAN DATA'!$D3306-'CLEAN DATA'!$L3306 -> 14680000
A3307: Lana Wachowski | B3307: 384 | C3307: 127 | D3307: 47375327 | E3307: Action|Adventure|Sci-Fi | F3307: Channing Tatum | G3307: Jupiter Ascending | H3307: 139593 | I3307: 720 | J3307: English | K3307: USA | L3307: 176000000 | M3307: 2015 | N3307: 5.4 | O3307: ='CLEAN DATA'!$D3307-'CLEAN DATA'!$L3307 -> -128624673
A3308: Tom Shadyac | B3308: 186 | C3308: 96 | D3308: 100289690 | E3308: Comedy|Family|Fantasy | F3308: Jimmy Bennett | G3308: Evan Almighty | H3308: 115099 | I3308: 257 | J3308: English | K3308: USA | L3308: 175000000 | M3308: 2007 | N3308: 5.4 | O3308: ='CLEAN DATA'!$D3308-'CLEAN DATA'!$L3308 -> -74710310
A3309: Simon Wells | B3309: 132 | C3309: 88 | D3309: 21379315 | E3309: Action|Adventure|Animation|Comedy|Family|Sci-Fi | F3309: Elisabeth Harnois | G3309: Mars Needs Moms | H3309: 17590 | I3309: 112 | J3309: English | K3309: USA | L3309: 150000000 | M3309: 2011 | N3309: 5.4 | O3309: ='CLEAN DATA'!$D3309-'CLEAN DATA'!$L3309 -> -128620685
...

Sheet MOVIE GENRE
A1: GENRE | B1: imdb_score | C1: MOVIES NAME | I1: GENRE | J1: Count of GENRE | K1: Average | L1: Median | M1: Mode | N1: Variance | O1: SD | P1: Max | Q1: Min
A2: Crime | B2: 9.3 | C2: The Shawshank Redemption | E2: =COUNTIF(D:D,A2) -> 0 | I2: Action | J2: 976 | K2: =AVERAGEIF(A:A,I2,B:B) -> 6.282582 | L2: {=MEDIAN(IF(A:A="Action",B:B))} -> 6.3 | M2: {=MODE(IF(A:A=I2,B:B))} -> 6.6 | N2: {=_xlfn.VAR.P(IF(A:A="Action",B:B))} -> 1.0820737 | O2: {=_xlfn.STDEV.S(IF(A:A="Action",B:B))} -> 1.040761 | P2: {=MAX(IF(A:A="Action",B:B))} -> 9 | Q2: {=MIN(IF(A:A="Action",B:B))} -> 2.1
A3: Crime | B3: 9.2 | C3: The Godfather | I3: Adventure | J3: 380 | K3: =AVERAGEIF(A:A,I3,B:B) -> 6.5457895 | L3: {=MEDIAN(IF(A:A="Adventure",B:B))} -> 6.7 | M3: 7.3 | N3: 1.3 | O3: 1.1 | P3: 8.6 | Q3: 2.3
A4: Action | B4: 9 | C4: The Dark Knight | I4: Animation | J4: 47 | K4: =AVERAGEIF(A:A,I4,B:B) -> 6.6978723 | L4: {=MEDIAN(IF(A:A="Animation",B:B))} -> 7 | M4: 7.1 | N4: 1 | O4: 1 | P4: 8 | Q4: 4.5
A5: Crime | B5: 9 | C5: The Godfather: Part II | I5: Biography | J5: 209 | K5: =AVERAGEIF(A:A,I5,B:B) -> 7.1454545 | L5: {=MEDIAN(IF(A:A="Biography",B:B))} -> 7.2 | M5: 7 | N5: 0.5 | O5: 0.7 | P5: 8.9 | Q5: 4.5
A6: Action | B6: 8.9 | C6: The Lord of the Rings: The Return of the King | I6: Comedy | J6: 1041 | K6: =AVERAGEIF(A:A,I6,B:B) -> 6.1565802 | L6: {=MEDIAN(IF(A:A="Comedy",B:B))} -> 6.3 | M6: 6.4 | N6: 1.1 | O6: 1 | P6: 8.8 | Q6: 1.9
A7: Biography | B7: 8.9 | C7: Schindler's List | I7: Crime | J7: 262 | K7: =AVERAGEIF(A:A,I7,B:B) -> 6.9244275 | L7: {=MEDIAN(IF(A:A="Crime",B:B))} -> 7 | M7: 7.4 | N7: 0.8 | O7: 0.9 | P7: 9.3 | Q7: 3.1
A8: Crime | B8: 8.9 | C8: Pulp Fiction | I8: Documentary | J8: 43 | K8: =AVERAGEIF(A:A,I8,B:B) -> 6.9511628 | L8: {=MEDIAN(IF(A:A="Documentary",B:B))} -> 7.3 | M8: 7.3 | N8: 4 | O8: 2 | P8: 8.5 | Q8: 1.6
A9: Western | B9: 8.9 | C9: The Good, the Bad and the Ugly | I9: Drama | J9: 704 | K9: =AVERAGEIF(A:A,I9,B:B) -> 6.8056818 | L9: {=MEDIAN(IF(A:A="Drama",B:B))} -> 6.9 | M9: 7.3 | N9: 0.8 | O9: 0.9 | P9: 8.8 | Q9: 2.1
A10: Action | B10: 8.8 | C10: Inception | I10: Family | J10: 3 | K10: =AVERAGEIF(A:A,I10,B:B) -> 6.5 | L10: {=MEDIAN(IF(A:A="Family",B:B))} -> 5.9 | M10: N/A | N10: 1.5 | O10: 1.2 | P10: 7.9 | Q10: 5.7
A11: Action | B11: 8.8 | C11: The Lord of the Rings: The Fellowship of the Ring | I11: Fantasy | J11: 37 | K11: =AVERAGEIF(A:A,I11,B:B) -> 6.2810811 | L11: {=MEDIAN(IF(A:A="Fantasy",B:B))} -> 6.5 | M11: 6.8 | N11: 0.8 | O11: 0.9 | P11: 7.9 | Q11: 4.3
A12: Drama | B12: 8.8 | C12: Fight Club | I12: Horror | J12: 173 | K12: =AVERAGEIF(A:A,I12,B:B) -> 5.8 | L12: {=MEDIAN(IF(A:A="Horror",B:B))} -> 5.8 | M12: 5.9 | N12: 1.1 | O12: 1.1 | P12: 8.5 | Q12: 2.2
A13: Comedy | B13: 8.8 | C13: Forrest Gump | I13: Musical | J13: 2 | K13: =AVERAGEIF(A:A,I13,B:B) -> 6.75 | L13: {=MEDIAN(IF(A:A="Musical",B:B))} -> 6.75 | M13: N/A | N13: N/A | O13: N/A | P13: 7.2 | Q13: 7.2
A14: Action | B14: 8.8 | C14: Star Wars: Episode V - The Empire Strikes Back | I14: Mystery | J14: 23 | K14: =AVERAGEIF(A:A,I14,B:B) -> 6.6521739 | L14: {=MEDIAN(IF(A:A="Mystery",B:B))} -> 6.7 | M14: 7.1 | N14: 1.2 | O14: 1.1 | P14: 8.5 | Q14: 3.3
A15: Action | B15: 8.7 | C15: The Lord of the Rings: The Two Towers | I15: Romance | J15: 2 | K15: =AVERAGEIF(A:A,I15,B:B) -> 6.65 | L15: {=MEDIAN(IF(A:A="Romance",B:B))} -> 6.65 | M15: N/A | N15: N/A | O15: N/A | P15: 7.1 | Q15: 7.1
A16: Action | B16: 8.7 | C16: The Matrix | I16: Sci-Fi | J16: 10 | K16: =AVERAGEIF(A:A,I16,B:B) -> 5.95 | L16: {=MEDIAN(IF(A:A="Sci-Fi",B:B))} -> 6.2 | M16: N/A | N16: 1.4 | O16: 1.2 | P16: 8.2 | Q16: 5
A17: Biography | B17: 8.7 | C17: Goodfellas | I17: Thriller | J17: 3 | K17: =AVERAGEIF(A:A,I17,B:B) -> 5.3 | L17: {=MEDIAN(IF(A:A="Thriller",B:B))} -> 4.8 | M17: N/A | N17: 0.6 | O17: 0.8 | P17: 4.5 | Q17: 3.4
A18: Action | B18: 8.7 | C18: Star Wars: Episode IV - A New Hope | I18: Western | J18: 4 | K18: =AVERAGEIF(A:A,I18,B:B) -> 6.45 | L18: {=MEDIAN(IF(A:A="Western",B:B))} -> 6.4 | M18: N/A | N18: 1.4 | O18: 2.5 | P18: 7.3 | Q18: 3.8
A19: Drama | B19: 8.7 | C19: One Flew Over the Cuckoo's Nest | I19: (blank)
A20: Crime | B20: 8.7 | C20: City of God | I20: Grand Total | J20: 3919
A21: Action | B21: 8.7 | C21: Seven Samurai
A22: Adventure | B22: 8.6 | C22: Interstellar
A23: Action | B23: 8.6 | C23: Saving Private Ryan | O23: AVERAGE | P23: =AVERAGE(J2:J18) -> 230.52941
A24: Crime | B24: 8.6 | C24: Se7en | O24: MEDIAN | P24: =MEDIAN(J2:J18) -> 43
A25: Crime | B25: 8.6 | C25: The Silence of the Lambs | O25: MODE | P25: =MODE(J2:J18) -> 3
A26: Adventure | B26: 8.6 | C26: Spirited Away | O26: MAX | P26: =MAX(J2:J18) -> 1041
A27: Crime | B27: 8.6 | C27: American History X | O27: Min | P27: =MIN(J2:J18) -> 2
A28: Crime | B28: 8.6 | C28: The Usual Suspects | O28: Var | P28: =VAR(J2:J18) -> 120073.76
A29: Comedy | B29: 8.6 | C29: Modern Times | O29: sd | P29: =_xlfn.STDEV.S(J2:J18) -> 346.51662
A30: Action | B30: 8.5 | C30: The Dark Knight Rises | O30: Range | P30: =P26-P27 -> 1039
A31: Action | B31: 8.5 | C31: Gladiator
A32: Action | B32: 8.5 | C32: Terminator 2: Judgment Day
A33: Drama | B33: 8.5 | C33: Django Unchained
A34: Crime | B34: 8.5 | C34: The Departed
A35: Adventure | B35: 8.5 | C35: The Lion King
A36: Crime | B36: 8.5 | C36: The Green Mile
A37: Drama | B37: 8.5 | C37: The Prestige
A38: Biography | B38: 8.5 | C38: The Pianist
A39: Drama | B39: 8.5 | C39: Apocalypse Now
A40: Action | B40: 8.5 | C40: Raiders of the Lost Ark
A41: Horror | B41: 8.5 | C41: Psycho
A42: Adventure | B42: 8.5 | C42: Back to the Future
... A3920: Documentary | B3920: 1.6 | C3920: Justin Bieber: Never Say Never

Sheet MOVIES DURATION
A1: duration | B1: imdb_score
A2: 142 | B2: 9.3
A3: 175 | B3: 9.2
A4: 152 | B4: 9
A5: 220 | B5: 9
A6: 192 | B6: 8.9
A7: 185 | B7: 8.9
A8: 178 | B8: 8.9 | D8: Average | E8: =AVERAGE(A:A) -> 109.778
A9: 142 | B9: 8.9 | D9: Median | E9: =MEDIAN(A:A) -> 106
A10: 148 | B10: 8.8 | D10: STD. | E10: =_xlfn.STDEV.S(A:A) -> 22.693099
A11: 171 | B11: 8.8
A12: 151 | B12: 8.8
A13: 142 | B13: 8.8
A14: 127 | B14: 8.8
A15: 172 | B15: 8.7
A16: 136 | B16: 8.7
A17: 146 | B17: 8.7
A18: 125 | B18: 8.7
A19: 133 | B19: 8.7
A20: 135 | B20: 8.7
A21: 202 | B21: 8.7
A22: 169 | B22: 8.6
... A3920: 115 | B3920: 1.6

Sheet LANGUAGE ANALYSIS
A1: movie_title | B1: language | C1: imdb_score | E1: language | F1: Count of Movies | G1: Average of imdb | H1: Median | I1: S.d
A2: The Shawshank Redemption | B2: English | C2: 9.3 | E2: Aboriginal | F2: 2 | G2: =AVERAGEIF(B:B,E3,C:C) -> 7.2 | H2: {=MEDIAN(IF(B:B=E2,C:C))} -> 6.95 | I2: {=_xlfn.STDEV.S(IF(B:B=E2,C:C))} -> 0.77781746
A3: The Godfather | B3: English | C3: 9.2 | E3: Arabic | F3: 1 | G3: =AVERAGEIF(B:B,E4,C:C) -> 7.1 | H3: {=MEDIAN(IF(B:B=E3,C:C))} -> 7.2 | I3: 0
A4: The Dark Knight | B4: English | C4: 9 | E4: Aramaic | F4: 1 | G4: =AVERAGEIF(B:B,E5,C:C) -> 4.3 | H4: {=MEDIAN(IF(B:B=E4,C:C))} -> 7.1 | I4: 0
A5: The Godfather: Part II | B5: English | C5: 9 | E5: Bosnian | F5: 1 | G5: =AVERAGEIF(B:B,E6,C:C) -> 7.2375 | H5: {=MEDIAN(IF(B:B=E5,C:C))} -> 4.3 | I5: 0
A6: The Lord of the Rings: The Return of the King | B6: English | C6: 8.9 | E6: Cantonese | F6: 8 | G6: =AVERAGEIF(B:B,E7,C:C) -> 7.4 | H6: {=MEDIAN(IF(B:B=E6,C:C))} -> 7.3 | I6: {=_xlfn.STDEV.S(IF(B:B=E6,C:C))} -> 0.44057592
A7: Schindler's List | B7: English | C7: 8.9 | E7: Czech | F7: 1 | G7: =AVERAGEIF(B:B,E8,C:C) -> 7.9 | H7: {=MEDIAN(IF(B:B=E7,C:C))} -> 7.4 | I7: 0
A8: Pulp Fiction | B8: English | C8: 8.9 | E8: Danish | F8: 3 | G8: =AVERAGEIF(B:B,E9,C:C) -> 7.5 | H8: {=MEDIAN(IF(B:B=E8,C:C))} -> 8.1 | I8: {=_xlfn.STDEV.S(IF(B:B=E8,C:C))} -> 0.52915026
A9: The Good, the Bad and the Ugly | B9: Italian | C9: 8.9 | E9: Dari | F9: 2 | G9: =AVERAGEIF(B:B,E10,C:C) -> 7.5666667 | H9: {=MEDIAN(IF(B:B=E9,C:C))} -> 7.5 | I9: {=_xlfn.STDEV.S(IF(B:B=E9,C:C))} -> 0.14142136
A10: Inception | B10: English | C10: 8.8 | E10: Dutch | F10: 3 | G10: =AVERAGEIF(B:B,E11,C:C) -> 7.5 | H10: {=MEDIAN(IF(B:B=E10,C:C))} -> 7.8 | I10: {=_xlfn.STDEV.S(IF(B:B=E10,C:C))} -> 0.40414519
A11: The Lord of the Rings: The Fellowship of the Ring | B11: English | C11: 8.8 | E11: Dzongkha | F11: 1 | G11: =AVERAGEIF(B:B,E12,C:C) -> 6.4096653 | H11: {=MEDIAN(IF(B:B=E11,C:C))} -> 7.5 | I11: 0
A12: Fight Club | B12: English | C12: 8.8 | E12: English | F12: 3735 | G12: =AVERAGEIF(B:B,E13,C:C) -> 6.7 | H12: {=MEDIAN(IF(B:B=E12,C:C))} -> 6.5 | I12: {=_xlfn.STDEV.S(IF(B:B=E12,C:C))} -> 1.0624452
A13: Forrest Gump | B13: English | C13: 8.8 | E13: Filipino | F13: 1 | G13: =AVERAGEIF(B:B,E14,C:C) -> 7.2864865 | H13: {=MEDIAN(IF(B:B=E13,C:C))} -> 6.7 | I13: 0
A14: Star Wars: Episode V - The Empire Strikes Back | B14: English | C14: 8.8 | E14: French | F14: 37 | G14: =AVERAGEIF(B:B,E15,C:C) -> 7.6923077 | H14: {=MEDIAN(IF(B:B=E14,C:C))} -> 7.2 | I14: {=_xlfn.STDEV.S(IF(B:B=E14,C:C))} -> 0.56132886
A15: The Lord of the Rings: The Two Towers | B15: English | C15: 8.7 | E15: German | F15: 13 | G15: =AVERAGEIF(B:B,E16,C:C) -> 7.5 | H15: {=MEDIAN(IF(B:B=E15,C:C))} -> 7.7 | I15: {=_xlfn.STDEV.S(IF(B:B=E15,C:C))} -> 0.64091281
A16: The Matrix | B16: English | C16: 8.7 | E16: Hebrew | F16: 3 | G16: =AVERAGEIF(B:B,E17,C:C) -> 6.76 | H16: {=MEDIAN(IF(B:B=E16,C:C))} -> 7.3 | I16: {=_xlfn.STDEV.S(IF(B:B=E16,C:C))} -> 0.43588989
A17: Goodfellas | B17: English | C17: 8.7 | E17: Hindi | F17: 10 | G17: =AVERAGEIF(B:B,E18,C:C) -> 7.1 | H17: {=MEDIAN(IF(B:B=E17,C:C))} -> 7.05 | I17: {=_xlfn.STDEV.S(IF(B:B=E17,C:C))} -> 1.1117554
A18: Star Wars: Episode IV - A New Hope | B18: English | C18: 8.7 | E18: Hungarian | F18: 1 | G18: =AVERAGEIF(B:B,E19,C:C) -> 6.9 | H18: {=MEDIAN(IF(B:B=E18,C:C))} -> 7.1 | I18: 0
A19: One Flew Over the Cuckoo's Nest | B19: English | C19: 8.7 | E19: Icelandic | F19: 1 | G19: =AVERAGEIF(B:B,E20,C:C) -> 7.9 | H19: {=MEDIAN(IF(B:B=E19,C:C))} -> 6.9 | I19: 0
A20: City of God | B20: Portuguese | C20: 8.7 | E20: Indonesian | F20: 2 | G20: =AVERAGEIF(B:B,E21,C:C) -> 7.1857143 | H20: {=MEDIAN(IF(B:B=E20,C:C))} -> 7.9 | I20: {=_xlfn.STDEV.S(IF(B:B=E20,C:C))} -> 0.42426407
A21: Seven Samurai | B21: Japanese | C21: 8.7 | E21: Italian | F21: 7 | G21: =AVERAGEIF(B:B,E22,C:C) -> 7.625 | H21: {=MEDIAN(IF(B:B=E21,C:C))} -> 7 | I21: {=_xlfn.STDEV.S(IF(B:B=E21,C:C))} -> 1.155319
A22: Interstellar | B22: English | C22: 8.6 | E22: Japanese | F22: 12 | G22: =AVERAGEIF(B:B,E23,C:C) -> 6 | H22: {=MEDIAN(IF(B:B=E22,C:C))} -> 7.8 | I22: {=_xlfn.STDEV.S(IF(B:B=E22,C:C))} -> 0.89962113
A23: Saving Private Ryan | B23: English | C23: 8.6 | E23: Kazakh | F23: 1 | G23: =AVERAGEIF(B:B,E24,C:C) -> 7.7 | H23: {=MEDIAN(IF(B:B=E23,C:C))} -> 6 | I23: 0
A24: Se7en | B24: English | C24: 8.6 | E24: Korean | F24: 5 | G24: =AVERAGEIF(B:B,E25,C:C) -> 7.08 | H24: {=MEDIAN(IF(B:B=E24,C:C))} -> 7.7 | I24: {=_xlfn.STDEV.S(IF(B:B=E24,C:C))} -> 0.57008771
A25: The Silence of the Lambs | B25: English | C25: 8.6 | E25: Mandarin | F25: 15 | G25: =AVERAGEIF(B:B,E26,C:C) -> 7.8 | H25: {=MEDIAN(IF(B:B=E25,C:C))} -> 7.4 | I25: {=_xlfn.STDEV.S(IF(B:B=E25,C:C))} -> 0.77201036
A26: Spirited Away | B26: Japanese | C26: 8.6 | E26: Maya | F26: 1 | G26: =AVERAGEIF(B:B,E27,C:C) -> 7.3 | H26: {=MEDIAN(IF(B:B=E26,C:C))} -> 7.8 | I26: 0
A27: American History X | B27: English | C27: 8.6 | E27: Mongolian | F27: 1 | G27: =AVERAGEIF(B:B,E28,C:C) -> 8.5 | H27: {=MEDIAN(IF(B:B=E27,C:C))} -> 7.3 | I27: 0
A28: The Usual Suspects | B28: English | C28: 8.6 | E28: None | F28: 1 | G28: =AVERAGEIF(B:B,E29,C:C) -> 7.15 | H28: {=MEDIAN(IF(B:B=E28,C:C))} -> 8.5 | I28: 0
A29: Modern Times | B29: English | C29: 8.6 | E29: Norwegian | F29: 4 | G29: =AVERAGEIF(B:B,E30,C:C) -> 8.1333333 | H29: {=MEDIAN(IF(B:B=E29,C:C))} -> 7.3 | I29: {=_xlfn.STDEV.S(IF(B:B=E29,C:C))} -> 0.57445626
A30: The Dark Knight Rises | B30: English | C30: 8.5 | E30: Persian | F30: 3 | G30: =AVERAGEIF(B:B,E31,C:C) -> 7.76 | H30: {=MEDIAN(IF(B:B=E30,C:C))} -> 8.4 | I30: {=_xlfn.STDEV.S(IF(B:B=E30,C:C))} -> 0.55075705
A31: Gladiator | B31: English | C31: 8.5 | E31: Portuguese | F31: 5 | G31: =AVERAGEIF(B:B,E32,C:C) -> 7.9 | H31: {=MEDIAN(IF(B:B=E31,C:C))} -> 8 | I31: {=_xlfn.STDEV.S(IF(B:B=E31,C:C))} -> 0.97877474
A32: Terminator 2: Judgment Day | B32: English | C32: 8.5 | E32: Romanian | F32: 1 | G32: =AVERAGEIF(B:B,E33,C:C) -> 6.5 | H32: {=MEDIAN(IF(B:B=E32,C:C))} -> 7.9 | I32: 0
A33: Django Unchained | B33: English | C33: 8.5 | E33: Russian | F33: 1 | G33: =AVERAGEIF(B:B,E34,C:C) -> 7.05 | H33: {=MEDIAN(IF(B:B=E33,C:C))} -> 6.5 | I33: 0
A34: The Departed | B34: English | C34: 8.5 | E34: Spanish | F34: 26 | G34: =AVERAGEIF(B:B,E35,C:C) -> 7.6 | H34: {=MEDIAN(IF(B:B=E34,C:C))} -> 7.15 | I34: {=_xlfn.STDEV.S(IF(B:B=E34,C:C))} -> 0.8261961
A35: The Lion King | B35: English | C35: 8.5 | E35: Swedish | F35: 1 | G35: =AVERAGEIF(B:B,E36,C:C) -> 8.4 | H35: {=MEDIAN(IF(B:B=E35,C:C))} -> 7.6 | I35: 0
A36: The Green Mile | B36: English | C36: 8.5 | E36: Telugu | F36: 1 | G36: =AVERAGEIF(B:B,E37,C:C) -> 6.6333333 | H36: {=MEDIAN(IF(B:B=E36,C:C))} -> 8.4 | I36: 0
A37: The Prestige | B37: English | C37: 8.5 | E37: Thai | F37: 3 | G37: =AVERAGEIF(B:B,E38,C:C) -> 7.4 | H37: {=MEDIAN(IF(B:B=E37,C:C))} -> 6.6 | I37: {=_xlfn.STDEV.S(IF(B:B=E37,C:C))} -> 0.45092498
A38: The Pianist | B38: English | C38: 8.5 | E38: Vietnamese | F38: 1 | G38: =AVERAGEIF(B:B,E39,C:C) -> 7.3 | H38: {=MEDIAN(IF(B:B=E38,C:C))} -> 7.4 | I38: 0
A39: Apocalypse Now | B39: English | C39: 8.5 | E39: Zulu | F39: 1 | G39: 7.1 | H39: {=MEDIAN(IF(B:B=E39,C:C))} -> 7.3 | I39: 1
A40: Raiders of the Lost Ark | B40: English | C40: 8.5 | E40: (blank)
A41: Psycho | B41: English | C41: 8.5 | E41: Grand Total | F41: 3916
A42: Back to the Future | B42: English | C42: 8.5
A43: Alien | B43: English | C43: 8.5
A44: Memento | B44: English | C44: 8.5
A45: Samsara | B45: None | C45: 8.5
A46: Whiplash | B46: English | C46: 8.5
A47: The Lives of Others | B47: German | C47: 8.5
A48: Children of Heaven | B48: Persian | C48: 8.5
A49: WALL·E | B49: English | C49: 8.4
A50: Braveheart | B50: English | C50: 8.4
A51: Amélie | B51: French | C51: 8.4
A52: Baahubali: The Beginning | B52: Telugu | C52: 8.4
A53: Star Wars: Episode VI - Return of the Jedi | B53: English | C53: 8.4
... A3917: Justin Bieber: Never Say Never | B3917: English | C3917: 1.6

Sheet TOP 10 DIRECTORS
A1: movie_title | B1: director_name | C1: imdb_score
A2: The Shawshank Redemption | B2: Frank Darabont | C2: 9.3 | G2: HIGHEST | H2: =LARGE(G10:G19,1) -> 8.6
A3: The Godfather | B3: Francis Ford Coppola | C3: 9.2 | F3: CONCLUSION | G3: PERCENTILE RANK | H3: =PERCENTRANK(G10:G19,8.6) -> 0.888
A4: The Dark Knight | B4: Christopher Nolan | C4: 9 | G4: PERCENTILE | H4: =PERCENTILE(G10:G19,H3) -> 8.5992
A5: The Godfather: Part II | B5: Francis Ford Coppola | C5: 9
A6: The Lord of the Rings: The Return of the King | B6: Peter Jackson | C6: 8.9
A7: Schindler's List | B7: Steven Spielberg | C7: 8.9
A8: Pulp Fiction | B8: Quentin Tarantino | C8: 8.9
A9: The Good, the Bad and the Ugly | B9: Sergio Leone | C9: 8.9 | F9: Top 10 Directors | G9: Average of imdb_score
A10: Inception | B10: Christopher Nolan | C10: 8.8 | F10: Charles Chaplin | G10: 8.6
A11: The Lord of the Rings: The Fellowship of the Ring | B11: Peter Jackson | C11: 8.8 | F11: Tony Kaye | G11: 8.6
A12: Fight Club | B12: David Fincher | C12: 8.8 | F12: Alfred Hitchcock | G12: 8.5
A13: Forrest Gump | B13: Robert Zemeckis | C13: 8.8 | F13: Damien Chazelle | G13: 8.5
A14: Star Wars: Episode V - The Empire Strikes Back | B14: Irvin Kershner | C14: 8.8 | F14: Majid Majidi | G14: 8.5
A15: The Lord of the Rings: The Two Towers | B15: Peter Jackson | C15: 8.7 | F15: Ron Fricke | G15: 8.5
A16: The Matrix | B16: Lana Wachowski | C16: 8.7 | F16: Sergio Leone | G16: 8.4333333
A17: Goodfellas | B17: Martin Scorsese | C17: 8.7 | F17: Christopher Nolan | G17: 8.425
A18: Star Wars: Episode IV - A New Hope | B18: George Lucas | C18: 8.7 | F18: Asghar Farhadi | G18: 8.4
A19: One Flew Over the Cuckoo's Nest | B19: Milos Forman | C19: 8.7 | F19: Marius A. Markevicius | G19: 8.4
A20: City of God | B20: Fernando Meirelles | C20: 8.7
A21: Seven Samurai | B21: Akira Kurosawa | C21: 8.7
A22: Interstellar | B22: Christopher Nolan | C22: 8.6
A23: Saving Private Ryan | B23: Steven Spielberg | C23: 8.6
A24: Se7en | B24: David Fincher | C24: 8.6
A25: The Silence of the Lambs | B25: Jonathan Demme | C25: 8.6
A26: Spirited Away | B26: Hayao Miyazaki | C26: 8.6
A27: American History X | B27: Tony Kaye | C27: 8.6
A28: The Usual Suspects | B28: Bryan Singer | C28: 8.6
A29: Modern Times | B29: Charles Chaplin | C29: 8.6
A30: The Dark Knight Rises | B30: Christopher Nolan | C30: 8.5
A31: Gladiator | B31: Ridley Scott | C31: 8.5
... A3920: Justin Bieber: Never Say Never | B3920: Jon M. Chu | C3920: 1.6

Sheet MOVIE BUDGET
A1: gross | B1: budget | C1: Profit
A2: 28341469 | B2: 25000000 | C2: ='CLEAN DATA'!$D2-'CLEAN DATA'!$L2 -> 3341469
A3: 134821952 | B3: 6000000 | C3: ='CLEAN DATA'!$D3-'CLEAN DATA'!$L3 -> 128821952
A4: 533316061 | B4: 185000000 | C4: ='CLEAN DATA'!$D4-'CLEAN DATA'!$L4 -> 348316061
A5: 57300000 | B5: 13000000 | C5: ='CLEAN DATA'!$D5-'CLEAN DATA'!$L5 -> 44300000
A6: 377019252 | B6: 94000000 | C6: ='CLEAN DATA'!$D6-'CLEAN DATA'!$L6 -> 283019252 | E6: CORRELATION
A7: 96067179 | B7: 22000000 | C7: ='CLEAN DATA'!$D7-'CLEAN DATA'!$L7 -> 74067179 | E7: =CORREL(A:A,B:B) -> 0.10217736
A8: 107930000 | B8: 8000000 | C8: ='CLEAN DATA'!$D8-'CLEAN DATA'!$L8 -> 99930000
A9: 6100000 | B9: 1200000 | C9: ='CLEAN DATA'!$D9-'CLEAN DATA'!$L9 -> 4900000
A10: 292568851 | B10: 160000000 | C10: ='CLEAN DATA'!$D10-'CLEAN DATA'!$L10 -> 132568851 | E10: Hight profit margin movie | F10: HIGHT PROFIT MARGIN
A11: 313837577 | B11: 93000000 | C11: ='CLEAN DATA'!$D11-'CLEAN DATA'!$L11 -> 220837577 | E11: The Hobbit: The Desolation of Smaug | F11: =MAX(C:C) -> 523505847
A12: 37023395 | B12: 63000000 | C12: ='CLEAN DATA'!$D12-'CLEAN DATA'!$L12 -> -25976605
A13: 329691196 | B13: 55000000 | C13: ='CLEAN DATA'!$D13-'CLEAN DATA'!$L13 -> 274691196
A14: 290158751 | B14: 18000000 | C14: ='CLEAN DATA'!$D14-'CLEAN DATA'!$L14 -> 272158751
A15: 340478898 | B15: 94000000 | C15: ='CLEAN DATA'!$D15-'CLEAN DATA'!$L15 -> 246478898
A16: 171383253 | B16: 63000000 | C16: ='CLEAN DATA'!$D16-'CLEAN DATA'!$L16 -> 108383253
A17: 46836394 | B17: 25000000 | C17: ='CLEAN DATA'!$D17-'CLEAN DATA'!$L17 -> 21836394
A18: 460935665 | B18: 11000000 | C18: ='CLEAN DATA'!$D18-'CLEAN DATA'!$L18 -> 449935665
A19: 112000000 | B19: 4400000 | C19: ='CLEAN DATA'!$D19-'CLEAN DATA'!$L19 -> 107600000
A20: 7563397 | B20: 3300000 | C20: ='CLEAN DATA'!$D20-'CLEAN DATA'!$L20 -> 4263397
A21: 269061 | B21: 2000000 | C21: ='CLEAN DATA'!$D21-'CLEAN DATA'!$L21 -> -1730939
A22: 187991439 | B22: 165000000 | C22: ='CLEAN DATA'!$D22-'CLEAN DATA'!$L22 -> 22991439
A23: 216119491 | B23: 70000000 | C23: ='CLEAN DATA'!$D23-'CLEAN DATA'!$L23 -> 146119491
... A3293: 8025872 | B3293: 4700000 | C3293: ='CLEAN DATA'!$D3293-'CLEAN DATA'!$L3293 -> 3325872
B3294: 2100000 | C3294: ='CLEAN DATA'!$D3294-'CLEAN DATA'!$L3294 -> -2100000
B3295: 2000000 | C3295: ='CLEAN DATA'!$D3295-'CLEAN DATA'!$L3295 -> -2000000
B3296: 1800000 | C3296: ='CLEAN DATA'!$D3296-'CLEAN DATA'!$L3296 -> -1800000
B3297: 1500000 | C3297: ='CLEAN DATA'!$D3297-'CLEAN DATA'!$L3297 -> -1500000
B3298: 1455000 | C3298: ='CLEAN DATA'!$D3298-'CLEAN DATA'!$L3298 -> -1455000
B3299: 3150000 | C3299: ='CLEAN DATA'!$D3299-'CLEAN DATA'!$L3299 -> -3150000
B3300: 1250000 | C3300: ='CLEAN DATA'!$D3300-'CLEAN DATA'!$L3300 -> -1250000
A3301: 79363785 | B3301: 80000000 | C3301: ='CLEAN DATA'!$D3301-'CLEAN DATA'!$L3301 -> -636215
A3302: 62480 | B3302: 1000000 | C3302: ='CLEAN DATA'!$D3302-'CLEAN DATA'!$L3302 -> -937520
A3303: 77501 | B3303: 750000 | C3303: ='CLEAN DATA'!$D3303-'CLEAN DATA'!$L3303 -> -672499
A3304: 40542 | B3304: 300000 | C3304: ='CLEAN DATA'!$D3304-'CLEAN DATA'!$L3304 -> -259458
A3305: 191309 | B3305: 150000 | C3305: ='CLEAN DATA'!$D3305-'CLEAN DATA'!$L3305 -> 41309
A3306: 15180000 | B3306: 500000 | C3306: ='CLEAN DATA'!$D3306-'CLEAN DATA'!$L3306 -> 14680000
A3307: 47375327 | B3307: 176000000 | C3307: ='CLEAN DATA'!$D3307-'CLEAN DATA'!$L3307 -> -128624673
A3308: 100289690 | B3308: 175000000 | C3308: ='CLEAN DATA'!$D3308-'CLEAN DATA'!$L3308 -> -74710310
A3309: 21379315 | B3309: 150000000 | C3309: ='CLEAN DATA'!$D3309-'CLEAN DATA'!$L3309 -> -128620685
A3310: 64736114 | B3310: 120000000 | C3310: ='CLEAN DATA'!$D3310-'CLEAN DATA'!$L3310 -> -55263886
A3311: 50026353 | B3311: 110000000 | C3311: ='CLEAN DATA'!$D3311-'CLEAN DATA'!$L3311 -> -59973647
A3312: 71017784 | B3312: 105000000 | C3312: ='CLEAN DATA'!$D3312-'CLEAN DATA'!$L3312 -> -33982216
... A3382: 703 | B3382: 1500000 | C3382: ='CLEAN DATA'!$D3382-'CLEAN DATA'!$L3382 -> -1499297
B3383: 500000 | C3383: ='CLEAN DATA'!$D3383-'CLEAN DATA'!$L3383 -> -500000
B3384: 2500000 | C3384: ='CLEAN DATA'!$D3384-'CLEAN DATA'!$L3384 -> -2500000
B3385: 10000000 | C3385: ='CLEAN DATA'!$D3385-'CLEAN DATA'!$L3385 -> -10000000
A3386: 30212620 | B3386: 120000000 | C3386: ='CLEAN DATA'!$D3386-'CLEAN DATA'!$L3386 -> -89787380
A3387: 28772222 | B3387: 105000000 | C3387: ='CLEAN DATA'!$D3387-'CLEAN DATA'!$L3387 -> -76227778
A3388: 67344392 | B3388: 92000000 | C3388: ='CLEAN DATA'!$D3388-'CLEAN DATA'!$L3388 -> -24655608
A3389: 39442871 | B3389: 80000000 | C3389: ='CLEAN DATA'!$D3389-'CLEAN DATA'!$L3389 -> -40557129
A3390: 30013346 | B3390: 75000000 | C3390: ='CLEAN DATA'!$D3390-'CLEAN DATA'!$L3390 -> -44986654
A3391: 144156464 | B3391: 71500000 | C3391: ='CLEAN DATA'!$D3391-'CLEAN DATA'!$L3391 -> 72656464
A3392: 48430355 | B3392: 70000000 | C3392: ='CLEAN DATA'!$D3392-'CLEAN DATA'!$L3392 -> -21569645
A3393: 50189179 | B3393: 60000000 | C3393: ='CLEAN DATA'!$D3393-'CLEAN DATA'!$L3393 -> -9810821
A3394: 20400913 | B3394: 45000000 | C3394: ='CLEAN DATA'!$D3394-'CLEAN DATA'!$L3394 -> -24599087
A3395: 26404753 | B3395: 40000000 | C3395: ='CLEAN DATA'!$D3395-'CLEAN DATA'!$L3395 -> -13595247
A3396: 28535768 | B3396: 40000000 | C3396: ='CLEAN DATA'!$D3396-'CLEAN DATA'!$L3396 -> -11464232
A3397: 5881504 | B3397: 39000000 | C3397: ='CLEAN DATA'!$D3397-'CLEAN DATA'!$L3397 -> -33118496
... A3493: 800000 | B3493: 14000000 | C3493: ='CLEAN DATA'!$D3493-'CLEAN DATA'!$L3493 -> -13200000
B3494: 10000000 | C3494: ='CLEAN DATA'!$D3494-'CLEAN DATA'!$L3494 -> -10000000
B3495: 10000000 | C3495: ='CLEAN DATA'!$D3495-'CLEAN DATA'!$L3495 -> -10000000
A3496: 25926543 | B3496: 8000000 | C3496: ='CLEAN DATA'!$D3496-'CLEAN DATA'!$L3496 -> 17926543
A3497: 20257000 | B3497: 7000000 | C3497: ='CLEAN DATA'!$D3497-'CLEAN DATA'!$L3497 -> 13257000
A3498: 11642254 | B3498: 3000000 | C3498: ='CLEAN DATA'!$D3498-'CLEAN DATA'!$L3498 -> 8642254
A3499: 25799043 | B3499: 3300000 | C3499: ='CLEAN DATA'!$D3499-'CLEAN DATA'!$L3499 -> 22499043
A3500: 17382982 | B3500: 5000000 | C3500: ='CLEAN DATA'!$D3500-'CLEAN DATA'!$L3500 -> 12382982
A3501: 17683670 | B3501: 5000000 | C3501: ='CLEAN DATA'!$D3501-'CLEAN DATA'!$L3501 -> 12683670
A3502: 4063 | B3502: 4000000 | C3502: ='CLEAN DATA'!$D3502-'CLEAN DATA'!$L3502 -> -3995937
A3503: 3293258 | B3503: 3000000 | C3503: ='CLEAN DATA'!$D3503-'CLEAN DATA'!$L3503 -> 293258
B3504: 1950000 | C3504: ='CLEAN DATA'!$D3504-'CLEAN DATA'!$L3504 -> -1950000
B3505: 1300000 | C3505: ='CLEAN DATA'!$D3505-'CLEAN DATA'!$L3505 -> -1300000
B3506: 1000000 | C3506: ='CLEAN DATA'!$D3506-'CLEAN DATA'!$L3506 -> -1000000
B3507: 1000000 | C3507: ='CLEAN DATA'!$D3507-'CLEAN DATA'!$L3507 -> -1000000
A3508: 18378 | B3508: 900000 | C3508: ='CLEAN DATA'!$D3508-'CLEAN DATA'!$L3508 -> -881622
A3509: 119420252 | B3509: 150000000 | C3509: ='CLEAN DATA'!$D3509-'CLEAN DATA'!$L3509 -> -30579748
A3510: 75030163 | B3510: 100000000 | C3510: ='CLEAN DATA'!$D3510-'CLEAN DATA'!$L3510 -> -24969837
A3511: 69102910 | B3511: 80000000 | C3511: ='CLEAN DATA'!$D3511-'CLEAN DATA'!$L3511 -> -10897090
A3512: 41814863 | B3512: 50000000 | C3512: ='CLEAN DATA'!$D3512-'CLEAN DATA'!$L3512 -> -8185137
A3513: 19059018 | B3513: 65000000 | C3513: ='CLEAN DATA'!$D3513-'CLEAN DATA'!$L3513 -> -45940982
A3514: 31054924 | B3514: 64000000 | C3514: ='CLEAN DATA'!$D3514-'CLEAN DATA'!$L3514 -> -32945076
A3515: 93815117 | B3515: 55000000 | C3515: ='CLEAN DATA'!$D3515-'CLEAN DATA'!$L3515 -> 38815117
A3516: 80270227 | B3516: 50000000 | C3516: ='CLEAN DATA'!$D3516-'CLEAN DATA'!$L3516 -> 30270227
A3517: 10400000 | B3517: 50000000 | C3517: ='CLEAN DATA'!$D3517-'CLEAN DATA'!$L3517 -> -39600000
A3518: 9795017 | B3518: 50000000 | C3518: ='CLEAN DATA'!$D3518-'CLEAN DATA'!$L3518 -> -40204983
A3519: 24430272 | B3519: 43000000 | C3519: ='CLEAN DATA'!$D3519-'CLEAN DATA'!$L3519 -> -18569728
... A3738: 186354 | B3738: 13500000 | C3738: ='CLEAN DATA'!$D3738-'CLEAN DATA'!$L3738 -> -13313646
B3739: 250000 | C3739: ='CLEAN DATA'!$D3739-'CLEAN DATA'!$L3739 -> -250000
B3740: 75000 | C3740: ='CLEAN DATA'!$D3740-'CLEAN DATA'!$L3740 -> -75000
A3741: 6712451 | B3741: 90000000 | C3741: ='CLEAN DATA'!$D3741-'CLEAN DATA'!$L3741 -> -83287549
A3742: 190562 | B3742: 90000000 | C3742: ='CLEAN DATA'!$D3742-'CLEAN DATA'!$L3742 -> -89809438
A3743: 133103929 | B3743: 75000000 | C3743: ='CLEAN DATA'!$D3743-'CLEAN DATA'!$L3743 -> 58103929
A3744: 66734992 | B3744: 60000000 | C3744: ='CLEAN DATA'!$D3744-'CLEAN DATA'!$L3744 -> 6734992
A3745: 61112916 | B3745: 50000000 | C3745: ='CLEAN DATA'!$D3745-'CLEAN DATA'!$L3745 -> 11112916
A3746: 38590500 | B3746: 50000000 | C3746: ='CLEAN DATA'!$D3746-'CLEAN DATA'!$L3746 -> -11409500
A3747: 27663982 | B3747: 40000000 | C3747: ='CLEAN DATA'!$D3747-'CLEAN DATA'!$L3747 -> -12336018
A3748: 511920 | B3748: 40000000 | C3748: ='CLEAN DATA'!$D3748-'CLEAN DATA'!$L3748 -> -39488080
A3749: 71038190 | B3749: 30000000 | C3749: ='CLEAN DATA'!$D3749-'CLEAN DATA'!$L3749 -> 41038190
A3750: 37911876 | B3750: 32000000 | C3750: ='CLEAN DATA'!$D3750-'CLEAN DATA'!$L3750 -> 5911876
A3751: 18500966 | B3751: 30000000 | C3751: ='CLEAN DATA'!$D3751-'CLEAN DATA'!$L3751 -> -11499034
...
